README
setup.cfg
setup.py
b88d80170_fake_data/__init__.py
b88d80170_fake_data/address.py
b88d80170_fake_data/application.py
b88d80170_fake_data/company.py
b88d80170_fake_data/date.py
b88d80170_fake_data/email.py
b88d80170_fake_data/generate.py
b88d80170_fake_data/name.py
b88d80170_fake_data/personal_data.py
b88d80170_fake_data/phone.py
b88d80170_fake_data/tsv.py
b88d80170_fake_data/utils.py
b88d80170_fake_data.egg-info/PKG-INFO
b88d80170_fake_data.egg-info/SOURCES.txt
b88d80170_fake_data.egg-info/dependency_links.txt
b88d80170_fake_data.egg-info/not-zip-safe
b88d80170_fake_data.egg-info/top_level.txt