Metadata-Version: 1.0
Name: b88d80170-fake-data
Version: 0.0.3
Summary: generate some random data
Home-page: UNKNOWN
Author: b88d80170
Author-email: b88d80170@gmail.com
License: UNKNOWN
Platform: UNKNOWN
